setup.py
BarkingOwl.egg-info/PKG-INFO
BarkingOwl.egg-info/SOURCES.txt
BarkingOwl.egg-info/dependency_links.txt
BarkingOwl.egg-info/not-zip-safe
BarkingOwl.egg-info/pbr.json
BarkingOwl.egg-info/requires.txt
BarkingOwl.egg-info/top_level.txt
barking_owl/__init__.py
barking_owl/busaccess.py
barking_owl/display_all.py
barking_owl/globalshutdown.py
barking_owl/dispatcher/__init__.py
barking_owl/dispatcher/barkingowl_dispatcher.py
barking_owl/dispatcher/dispatcher.py
barking_owl/scraper/__init__.py
barking_owl/scraper/barkingowl_scraper.py
barking_owl/scraper/cli-scraper.py
barking_owl/scraper/interface.py
barking_owl/scraper/scraper.py
barking_owl/scraper/scraperwrapper.py