Metadata-Version: 1.1
Name: BarkingOwl
Version: 0.8.1
Summary: Scalable web crawler.
Home-page: https://github.com/thequbit/BarkingOwl
Author: Timothy Duffy
Author-email: tim@timduffy.me
License: GPL3
Platform: any
Classifier: Development Status :: 4 - Beta
Classifier: Environment :: Console
Classifier: Intended Audience :: Developers
Classifier: License :: OSI Approved :: GNU General Public License v3 (GPLv3)
